{
  "code": 1000,
  "data": {
    "list": [
      {
        "brandId": 20,
        "brandLogo": "315826e7-191c-4ba7-a84c-e43e1403793f.png",
        "brandNameCh": "Swisse",
        "brandNameEn": "Swisse",
        "country": "澳大利亚",
        "couponPrice": null,
        "inventory": 4072,
        "itemCode": "DIM161121190329001338",
        "itemLogoUrl": "https://img.allpyra.com/4fcf6bb3-6a8e-43ee-adbb-61e828548714.jpg",
        "itemTitle": "Swisse 月见草油软胶囊 200粒",
        "itemType": null,
        "marketPrice": 198.00,
        "maxBuyCount": 5,
        "productCode": "P161108170824001717",
        "putaway": "UP",
        "rebateMoney": 0,
        "recommend": "Swisse 月见草油软胶囊能有效调节内分泌，改善经期平衡。恢复皮肤细腻光泽，减少黄褐斑粉刺，缓解肿块丰胸挺乳，还能控制体重，促进心脑健康。",
        "salePrice": 149.00,
        "warehouseCode": "202",
        "warehouseName": "东莞邮政仓"
      },
      {
        "brandId": 41,
        "brandLogo": "400927ff-d84b-4272-b35d-1bb3b9661982.jpg",
        "brandNameCh": "爱茉莉",
        "brandNameEn": "Amore",
        "country": "韩国",
        "couponPrice": null,
        "inventory": 556,
        "itemCode": "DIM161121135023001263",
        "itemLogoUrl": "https://img.allpyra.com/70bbbfa4-085f-4d4c-9b80-84243edf14b4.jpg",
        "itemTitle": "AMORE爱茉莉 麦迪安牙膏86% 红色3支装",
        "itemType": null,
        "marketPrice": 99.00,
        "maxBuyCount": 3,
        "productCode": "P161108181319001175",
        "putaway": "UP",
        "rebateMoney": 0,
        "recommend": "爱茉莉牙膏麦迪安牙膏86%采用医学安全级别的牙垢溶解剂，快速溶解牙石，不用蛮力刷牙。\n",
        "salePrice": 65.00,
        "warehouseCode": "202",
        "warehouseName": "东莞邮政仓"
      },
      {
        "brandId": 304,
        "brandLogo": "13510adf-6635-4054-805f-f458c54c60aa.jpg",
        "brandNameCh": "悦诗风吟",
        "brandNameEn": "innisfree",
        "country": "韩国",
        "couponPrice": null,
        "inventory": 56,
        "itemCode": "DIM161121105857001112",
        "itemLogoUrl": "https://img.allpyra.com/dc172091-7d1a-4c27-b61e-44a020345902.jpg",
        "itemTitle": "innisfree悦诗风吟 绿茶精萃滋润面霜 50ml",
        "itemType": null,
        "marketPrice": 168.00,
        "maxBuyCount": 10,
        "productCode": "P161110101302001156",
        "putaway": "UP",
        "rebateMoney": 0,
        "recommend": "Innisfree（悦诗风吟）是韩国化妆品品牌，也是由韩国第一化妆品集团AmorePacific爱茉莉太平洋集团潜心研制的自然主义化妆品，是高科技和自然的完美结合。这一品牌的推出是基于90年代末对于都市女性所作的全面调研，寻找到了都市女性心目中所向往的未来的化妆品的特性：自然、健康、朴素、时尚。从推出第一支产品迄今，悦诗风吟一直坚持这些理念，并运用先进科技，不断对品牌进行提升，追求自然与肌肤的完美融合。\n",
        "salePrice": 129.00,
        "warehouseCode": "DF-ZU-10",
        "warehouseName": "阿威普香港直邮代发仓"
      },
      {
        "brandId": 57,
        "brandLogo": "725679a6-dd86-4990-8c11-025159ae0e9e.jpg",
        "brandNameCh": "九朵云",
        "brandNameEn": "Cloud9",
        "country": "韩国",
        "couponPrice": null,
        "inventory": 443,
        "itemCode": "DIM161122144923001534",
        "itemLogoUrl": "https://img.allpyra.com/2381cfe5-0903-4254-ac53-27a2e9bfab14.jpg",
        "itemTitle": "CLOUD9九朵云 美白淡斑面霜 50ml",
        "itemType": null,
        "marketPrice": 129.00,
        "maxBuyCount": 10,
        "productCode": "P161108164800001534",
        "putaway": "UP",
        "rebateMoney": 0,
        "recommend": "九朵云美白淡斑面霜50ml，由9种植物提取，膏体如同云般轻柔细腻，韩国药店专卖产品，在韩国电视购物频道“乐天电视购物”创40分钟全部售磬，一分钟934个的销售记录，缓解紫外线造成的红肿。",
        "salePrice": 109.00,
        "warehouseCode": "202",
        "warehouseName": "东莞邮政仓"
      },
      {
        "brandId": 253,
        "brandLogo": "aefaf8ce-71e8-48a3-ac16-24926ba27b7e.jpg",
        "brandNameCh": "曼丹",
        "brandNameEn": "Mandom",
        "country": "日本",
        "couponPrice": null,
        "inventory": 400,
        "itemCode": "DIM161125155033001062",
        "itemLogoUrl": "https://img.allpyra.com/8f05e615-25f9-4c21-a385-b1b170cba22d.jpg",
        "itemTitle": "MANDOM曼丹 弹力紧致面膜 5片（橙色）",
        "itemType": null,
        "marketPrice": 120.00,
        "maxBuyCount": 10,
        "productCode": "P161109191232001454",
        "putaway": "UP",
        "rebateMoney": 0,
        "recommend": "Mandom曼丹Barrier Repair面膜每片面膜含丰富美容精华液，主要是采用玻尿酸为保湿成分，而且将其进行小分子化，所含的玻尿酸分子比普通玻尿酸分子更小，更容易被肌肤所吸收。主要作用是特润，加倍保湿补水，令肌肤回复婴儿般的柔嫩。",
        "salePrice": 72.00,
        "warehouseCode": "202",
        "warehouseName": "东莞邮政仓"
      },
      {
        "brandId": 9,
        "brandLogo": "e63201c3-696a-473f-b14d-c98856748c28.png",
        "brandNameCh": "喜宝",
        "brandNameEn": "HiPP",
        "country": "德国",
        "couponPrice": null,
        "inventory": 214,
        "itemCode": "DIM161121154858001090",
        "itemLogoUrl": "https://img.allpyra.com/62cba9e0-8d5e-493b-9abb-fd79fc6edd4d.jpg",
        "itemTitle": "有效期2017年12月HiPP德国喜宝有机奶粉2段 （6-10个月宝宝）800g",
        "itemType": null,
        "marketPrice": 199.00,
        "maxBuyCount": 5,
        "productCode": "P161108153604001111",
        "putaway": "UP",
        "rebateMoney": 0,
        "recommend": "喜宝有机奶粉，忠于取之自然 还予自然的理念，采用全天然有机的食品原料精心加工制作而成，清新无污染，来自源头的健康保证。为有助宝宝大脑发育，不加糖、香料，防腐剂，添加独有OMEGA3不饱和脂肪酸。现在喜宝公司已是欧洲最大的有机婴儿食品生产商。",
        "salePrice": 116.00,
        "warehouseCode": "202",
        "warehouseName": "东莞邮政仓"
      },
      {
        "brandId": 26,
        "brandLogo": "3d144a8e-8a06-4058-966f-f2645137664f.jpg",
        "brandNameCh": "JAYJUN",
        "brandNameEn": "JAYJUN",
        "country": "韩国",
        "couponPrice": null,
        "inventory": 190,
        "itemCode": "DIM161125160142001136",
        "itemLogoUrl": "https://img.allpyra.com/b0785d63-30ff-4d56-85b1-7b06669b837e.jpg",
        "itemTitle": " JAYJUN樱花童颜水光焕白面膜三部曲10片 韩国国民面膜 网红达人爱用",
        "itemType": null,
        "marketPrice": 139.00,
        "maxBuyCount": 10,
        "productCode": "P161108161501001297",
        "putaway": "UP",
        "rebateMoney": 0,
        "recommend": "韩国国民面膜，网红达人推荐使用的一款焕白面膜，同时拥有精华、面膜、面霜、颈霜的效果，滋润保湿焕白紧致一片搞定！有效缓解法令纹和颈纹，富含大量的骨胶原蛋白精华，360度无死角全脸滋润修护，打造白嫩婴儿肌！ ",
        "salePrice": 112.00,
        "warehouseCode": "202",
        "warehouseName": "东莞邮政仓"
      },
      {
        "brandId": 265,
        "brandLogo": "d359308e-d1ee-446b-b497-3eab37ddd1f6.jpg",
        "brandNameCh": "佑天兰",
        "brandNameEn": "Utena",
        "country": "日本",
        "couponPrice": null,
        "inventory": 18,
        "itemCode": "DIM161121184715001250",
        "itemLogoUrl": "https://img.allpyra.com/376cd369-5a83-4da7-a6f9-fb800e11a389.jpg",
        "itemTitle": "UTENA佑天兰 蜂蜜保湿黄金果冻面膜 黄色3片/盒",
        "itemType": null,
        "marketPrice": 138.00,
        "maxBuyCount": 10,
        "productCode": "P161109102015001297",
        "putaway": "UP",
        "rebateMoney": 0,
        "recommend": "Utena佑天兰PREMIUMPURESA黄金果冻面膜能使肌肤从体内及皮肤表层吸得大量的水份，增强皮肤长时间的保水能力。\n",
        "salePrice": 76.00,
        "warehouseCode": "202",
        "warehouseName": "东莞邮政仓"
      },
      {
        "brandId": 121,
        "brandLogo": "382d0d48-b3ee-4de2-90a5-21d0c3391a8d.gif",
        "brandNameCh": "美迪恵尔",
        "brandNameEn": "Mediheal",
        "country": "韩国",
        "couponPrice": null,
        "inventory": 1590,
        "itemCode": "DIM161121151943001003",
        "itemLogoUrl": "https://img.allpyra.com/88a3967f-7529-428a-8e03-dc021e8d3436.jpg",
        "itemTitle": "MEDIHEAL可莱丝 LINE限量版清澈透亮I.P.I面膜 10片装",
        "itemType": null,
        "marketPrice": 180.00,
        "maxBuyCount": 10,
        "productCode": "P161108165850001620",
        "putaway": "UP",
        "rebateMoney": 0,
        "recommend": "MEDIHEAL可莱 LINE限量版面膜，蓝色全家福保湿补水，收敛毛孔；黄色布朗熊紧致弹力；粉色可妮兔清澈透白；绿色莎莉鸭镇定舒缓。\n\n",
        "salePrice": 112.00,
        "warehouseCode": "202",
        "warehouseName": "东莞邮政仓"
      },
      {
        "brandId": 26,
        "brandLogo": "3d144a8e-8a06-4058-966f-f2645137664f.jpg",
        "brandNameCh": "JAYJUN",
        "brandNameEn": "JAYJUN",
        "country": "韩国",
        "couponPrice": null,
        "inventory": 239,
        "itemCode": "DIM161121111017001163",
        "itemLogoUrl": "https://img.allpyra.com/a53946c1-f009-4a53-9d78-65e8d0135e71.jpg",
        "itemTitle": "JAYJUN 美白补水黑色水光面膜 10片/盒",
        "itemType": null,
        "marketPrice": 168.00,
        "maxBuyCount": 10,
        "productCode": "P161108161501001295",
        "putaway": "UP",
        "rebateMoney": 0,
        "recommend": "JAYJUN 水光三部曲面膜，集洁面，补水，白嫩，水光于一身的多功能面膜！仿人皮的面膜材质让精华素植入皮肤肌底，毛孔瞬间缩小，带来的可不是流于表面的功效，而是由内而外的水润透白！~\n",
        "salePrice": 138.00,
        "warehouseCode": "202",
        "warehouseName": "东莞邮政仓"
      }
    ],
    "startNum": 20
  },
  "desc": "成功",
  "tid": "4aaa9f9f-1d15-43ed-8e2f-f2d418f918ef"
}
